setup.py
rollbot_crawlab/__init__.py
rollbot_crawlab.egg-info/PKG-INFO
rollbot_crawlab.egg-info/SOURCES.txt
rollbot_crawlab.egg-info/dependency_links.txt
rollbot_crawlab.egg-info/top_level.txt
rollbot_crawlab/cli/__init__.py
rollbot_crawlab/config/__init__.py
rollbot_crawlab/constants/__init__.py
rollbot_crawlab/core/__init__.py
rollbot_crawlab/core/client.py
rollbot_crawlab/core/config.py
rollbot_crawlab/core/log.py
rollbot_crawlab/core/request.py
rollbot_crawlab/db/__init__.py
rollbot_crawlab/db/es.py
rollbot_crawlab/db/kafka.py
rollbot_crawlab/db/mongo.py
rollbot_crawlab/db/sql.py
rollbot_crawlab/files/__init__.py
rollbot_crawlab/pipelines/__init__.py
rollbot_crawlab/utils/__init__.py
rollbot_crawlab/utils/config.py
rollbot_crawlab/utils/data.py
rollbot_crawlab/utils/item.py
rollbot_crawlab/utils/oss_file_upload.py
rollbot_crawlab/utils/scrapy.py
rollbot_crawlab/utils/source.py