Metadata-Version: 1.0
Name: rollbot-crawlab
Version: 0.1.7
Summary: rollbot crawlab
Home-page: UNKNOWN
Author: zengjin
Author-email: jzeng@rollong.com
License: MIT Licence
Keywords: pip,pathtool,timetool,magetool,mage
Platform: any
